sqlite_bedrock_packs/__init__.py
sqlite_bedrock_packs/_db_attachable.py
sqlite_bedrock_packs/_db_behavior_pack.py
sqlite_bedrock_packs/_db_bp_animation.py
sqlite_bedrock_packs/_db_bp_animation_controller.py
sqlite_bedrock_packs/_db_bp_block.py
sqlite_bedrock_packs/_db_bp_item.py
sqlite_bedrock_packs/_db_client_entity.py
sqlite_bedrock_packs/_db_entity.py
sqlite_bedrock_packs/_db_feature.py
sqlite_bedrock_packs/_db_feature_rule.py
sqlite_bedrock_packs/_db_geometry.py
sqlite_bedrock_packs/_db_loot_table.py
sqlite_bedrock_packs/_db_particle.py
sqlite_bedrock_packs/_db_render_controller.py
sqlite_bedrock_packs/_db_resource_pack.py
sqlite_bedrock_packs/_db_rp_animation.py
sqlite_bedrock_packs/_db_rp_animation_controller.py
sqlite_bedrock_packs/_db_rp_item.py
sqlite_bedrock_packs/_db_sound.py
sqlite_bedrock_packs/_db_sound_definitions.py
sqlite_bedrock_packs/_db_terrain_texture.py
sqlite_bedrock_packs/_db_texture.py
sqlite_bedrock_packs/_db_trade_table.py
sqlite_bedrock_packs/_views.py
sqlite_bedrock_packs/py.typed
sqlite_bedrock_packs/utils.py
sqlite_bedrock_packs/views.py
sqlite_bedrock_packs/views.pyi
sqlite_bedrock_packs/better_json_tools/__init__.py
sqlite_bedrock_packs/better_json_tools/compact_encoder.py
sqlite_bedrock_packs/better_json_tools/json_walker.py
sqlite_bedrock_packs/better_json_tools/jsonc.py
sqlite_bedrock_packs/better_json_tools/py.typed
sqlite_bedrock_packs-3.2.0.dist-info/LICENSE
sqlite_bedrock_packs-3.2.0.dist-info/METADATA
sqlite_bedrock_packs-3.2.0.dist-info/WHEEL
sqlite_bedrock_packs-3.2.0.dist-info/top_level.txt
sqlite_bedrock_packs-3.2.0.dist-info/RECORD
