Metadata-Version: 2.1
Name: sqlite-bedrock-packs
Version: 3.2.0
Summary: Python package that loads data from Minecraft: Bedrock Edition packs into SQLite database
Author: Nusiq
License: MIT
Project-URL: Source, https://github.com/Nusiq/sqlite_bedrock_packs/tree/master
Project-URL: Documentation, https://sqlite-bedrock-packs.readthedocs.io/en/stable/
Classifier: Development Status :: 5 - Production/Stable
Classifier: License :: OSI Approved :: MIT License
Classifier: Programming Language :: Python :: 3.10
Requires-Python: >=3.10
License-File: LICENSE
